{"text":1382,"subject":[
{"word": "journée", "value":3.09791}
,{"word": "pdia", "value":6.81756}
,{"word": "journée", "value":3.09791}
,{"word": "pdia", "value":6.81756}
],"content":[
{"word": "cher", "value":3.79713}
,{"word": "adhérent", "value":4.70734}
,{"word": "cher", "value":3.79713}
,{"word": "adhérent", "value":4.70734}
,{"word": "l", "value":1.55233}
,{"word": "association", "value":2.08136}
,{"word": "française", "value":2.49012}
,{"word": "pour", "value":0.939318}
,{"word": "l", "value":1.55233}
,{"word": "intelligence", "value":5.03207}
,{"word": "artificielle", "value":5.88488}
,{"word": "organise", "value":3.05056}
,{"word": "une", "value":0.934198}
,{"word": "journée", "value":13.6233}
,{"word": "d", "value":0.414827}
,{"word": "interventions", "value":4.0142}
,{"word": "et", "value":0.889284}
,{"word": "de", "value":0.428779}
,{"word": "prospective", "value":4.25261}
,{"word": "en", "value":0.80273}
,{"word": "intelligence", "value":5.03207}
,{"word": "artificielle", "value":5.88488}
,{"word": "en", "value":0.80273}
,{"word": "l", "value":1.55233}
,{"word": "honneur", "value":4.23356}
,{"word": "des", "value":0.591823}
,{"word": "eccai", "value":5.11281}
,{"word": "fellows", "value":5.80596}
,{"word": "français", "value":1.58378}
,{"word": "élus", "value":10.8625}
,{"word": "en", "value":0.80273}
,{"word": "cette", "value":4.11175}
,{"word": "journée", "value":13.6233}
,{"word": "se", "value":1.6977}
,{"word": "tiendra", "value":2.84727}
,{"word": "sous", "value":2.94805}
,{"word": "le", "value":0.774863}
,{"word": "patronage", "value":5.56479}
,{"word": "du", "value":0.911334}
,{"word": "mesr", "value":9.89151}
,{"word": "dgri", "value":10.2256}
,{"word": "du", "value":0.911334}
,{"word": "cnrs", "value":7.60505}
,{"word": "ins", "value":8.79438}
,{"word": "i", "value":4.22961}
,{"word": "et", "value":0.889284}
,{"word": "d", "value":0.414827}
,{"word": "inria", "value":5.74798}
,{"word": "accueil", "value":2.46085}
,{"word": "des", "value":0.591823}
,{"word": "participants", "value":2.37491}
,{"word": "ouverture", "value":2.91558}
,{"word": "avec", "value":0.635472}
,{"word": "des", "value":0.591823}
,{"word": "représentants", "value":5.15933}
,{"word": "de", "value":0.428779}
,{"word": "l", "value":1.55233}
,{"word": "afia", "value":20.1079}
,{"word": "du", "value":0.911334}
,{"word": "mesr", "value":9.89151}
,{"word": "dgri", "value":10.2256}
,{"word": "du", "value":0.911334}
,{"word": "cnrs", "value":7.60505}
,{"word": "ins", "value":8.79438}
,{"word": "i", "value":4.22961}
,{"word": "et", "value":0.889284}
,{"word": "d", "value":0.414827}
,{"word": "inria", "value":5.74798}
,{"word": "andreas", "value":6.12441}
,{"word": "herzig", "value":6.41209}
,{"word": "irit", "value":6.40628}
,{"word": "cnrs", "value":7.60505}
,{"word": "quelles", "value":3.41636}
,{"word": "logiques", "value":3.87312}
,{"word": "pour", "value":0.939318}
,{"word": "les", "value":0.618975}
,{"word": "systèmes", "value":1.21084}
,{"word": "multi", "value":1.89575}
,{"word": "agents", "value":2.53053}
,{"word": "françois", "value":2.93085}
,{"word": "pachet", "value":5.6389}
,{"word": "sony", "value":12.8242}
,{"word": "csl", "value":6.41209}
,{"word": "sony", "value":12.8242}
,{"word": "créativité", "value":4.25261}
,{"word": "et", "value":0.889284}
,{"word": "style", "value":2.71491}
,{"word": "de", "value":0.428779}
,{"word": "nouveaux", "value":2.23259}
,{"word": "problèmes", "value":4.46008}
,{"word": "pour", "value":0.939318}
,{"word": "l", "value":1.55233}
,{"word": "ia", "value":4.96708}
,{"word": "hélène", "value":4.19652}
,{"word": "fargier", "value":6.25794}
,{"word": "irit", "value":6.40628}
,{"word": "cnrs", "value":7.60505}
,{"word": "problèmes", "value":4.46008}
,{"word": "combinatoires", "value":5.80596}
,{"word": "de", "value":0.428779}
,{"word": "décision", "value":2.07917}
,{"word": "sous", "value":2.94805}
,{"word": "incertitude", "value":3.52172}
,{"word": "buffet", "value":4.54029}
,{"word": "jérôme", "value":3.0448}
,{"word": "euzenat", "value":4.83656}
,{"word": "lig", "value":2.71905}
,{"word": "inria", "value":5.74798}
,{"word": "représenter", "value":3.99916}
,{"word": "communiquer", "value":4.07672}
,{"word": "échouer", "value":6.81756}
,{"word": "leila", "value":5.43126}
,{"word": "amgoud", "value":6.59441}
,{"word": "irit", "value":6.40628}
,{"word": "cnrs", "value":7.60505}
,{"word": "la", "value":0.253358}
,{"word": "théorie", "value":3.17997}
,{"word": "computationnelle", "value":4.56627}
,{"word": "de", "value":0.428779}
,{"word": "l", "value":1.55233}
,{"word": "argumentation", "value":4.98498}
,{"word": "cette", "value":4.11175}
,{"word": "journée", "value":13.6233}
,{"word": "sera", "value":3.30653}
,{"word": "suivie", "value":4.21487}
,{"word": "de", "value":0.428779}
,{"word": "l", "value":1.55233}
,{"word": "assemblée", "value":8.3216}
,{"word": "générale", "value":6.0554}
,{"word": "ordinaire", "value":9.41469}
,{"word": "de", "value":0.428779}
,{"word": "l", "value":1.55233}
,{"word": "afia", "value":20.1079}
,{"word": "incluant", "value":3.42473}
,{"word": "bilans", "value":5.71894}
,{"word": "prévisions", "value":5.80596}
,{"word": "dont", "value":1.94236}
,{"word": "créations", "value":6.41209}
,{"word": "d", "value":0.414827}
,{"word": "un", "value":0.223828}
,{"word": "club", "value":5.37064}
,{"word": "industriel", "value":2.58345}
,{"word": "et", "value":0.889284}
,{"word": "conférence", "value":1.23218}
,{"word": "sur", "value":0.782336}
,{"word": "les", "value":0.618975}
,{"word": "applications", "value":1.26266}
,{"word": "pratiques", "value":2.1975}
,{"word": "de", "value":0.428779}
,{"word": "l", "value":1.55233}
,{"word": "ia", "value":4.96708}
,{"word": "et", "value":0.889284}
,{"word": "sera", "value":3.30653}
,{"word": "précédée", "value":5.71894}
,{"word": "par", "value":0.445091}
,{"word": "une", "value":0.934198}
,{"word": "intervention", "value":3.94117}
,{"word": "des", "value":0.591823}
,{"word": "élus", "value":10.8625}
,{"word": "de", "value":0.428779}
,{"word": "l", "value":1.55233}
,{"word": "afia", "value":20.1079}
,{"word": "dans", "value":0.279779}
,{"word": "les", "value":0.618975}
,{"word": "sections", "value":14.5097}
,{"word": "et", "value":0.889284}
,{"word": "du", "value":0.911334}
,{"word": "conrs", "value":18.0199}
,{"word": "marie", "value":2.24801}
,{"word": "christine", "value":3.03907}
,{"word": "rousset", "value":4.76986}
,{"word": "conrs", "value":18.0199}
,{"word": "section", "value":6.41328}
,{"word": "et", "value":0.889284}
,{"word": "philippe", "value":2.48682}
,{"word": "fraisse", "value":6.25794}
,{"word": "conrs", "value":18.0199}
,{"word": "section", "value":6.41328}
,{"word": "bilan", "value":4.54029}
,{"word": "concours", "value":3.05636}
,{"word": "cnrs", "value":7.60505}
,{"word": "sections", "value":14.5097}
,{"word": "et", "value":0.889284}
,{"word": "sections", "value":14.5097}
,{"word": "assemblée", "value":8.3216}
,{"word": "générale", "value":6.0554}
,{"word": "ordinaire", "value":9.41469}
,{"word": "de", "value":0.428779}
,{"word": "l", "value":1.55233}
,{"word": "afia", "value":20.1079}
,{"word": "cocktail", "value":4.54029}
,{"word": "cette", "value":4.11175}
,{"word": "journée", "value":13.6233}
,{"word": "exceptionnelle", "value":7.5107}
,{"word": "aura", "value":1.98725}
,{"word": "lieu", "value":1.09643}
,{"word": "le", "value":0.774863}
,{"word": "octobre", "value":4.24326}
,{"word": "à", "value":0.325921}
,{"word": "l", "value":1.55233}
,{"word": "université", "value":0.668021}
,{"word": "paris", "value":0.94826}
,{"word": "dauphine", "value":4.04497}
,{"word": "en", "value":0.80273}
,{"word": "salle", "value":2.99437}
,{"word": "a", "value":2.12993}
,{"word": "l", "value":1.55233}
,{"word": "accès", "value":4.15396}
,{"word": "à", "value":0.325921}
,{"word": "la", "value":0.253358}
,{"word": "journée", "value":13.6233}
,{"word": "pdia", "value":10.1367}
,{"word": "sera", "value":3.30653}
,{"word": "limité", "value":4.1785}
,{"word": "aux", "value":0.616034}
,{"word": "seules", "value":4.94575}
,{"word": "personnes", "value":2.15885}
,{"word": "qui", "value":0.734767}
,{"word": "se", "value":1.6977}
,{"word": "seront", "value":1.21084}
,{"word": "inscrites", "value":5.06836}
,{"word": "sur", "value":0.782336}
,{"word": "le", "value":0.774863}
,{"word": "site", "value":2.95702}
,{"word": "site", "value":2.95702}
,{"word": "des", "value":0.591823}
,{"word": "inscriptions", "value":4.9475}
,{"word": "avant", "value":3.82827}
,{"word": "le", "value":0.774863}
,{"word": "septembre", "value":4.36081}
,{"word": "journée", "value":13.6233}
,{"word": "pdia", "value":10.1367}
,{"word": "http", "value":0.555942}
,{"word": "www", "value":0.599953}
,{"word": "afia", "value":20.1079}
,{"word": "asso", "value":5.29405}
,{"word": "fr", "value":0.340386}
,{"word": "tiki", "value":3.82182}
,{"word": "index", "value":2.60914}
,{"word": "php", "value":2.20989}
,{"word": "page", "value":2.02383}
,{"word": "journ", "value":4.59293}
,{"word": "c", "value":3.529}
,{"word": "a", "value":2.12993}
,{"word": "e", "value":2.29191}
,{"word": "pour", "value":0.939318}
,{"word": "la", "value":0.253358}
,{"word": "promotion", "value":4.06072}
,{"word": "et", "value":0.889284}
,{"word": "le", "value":0.774863}
,{"word": "d", "value":0.414827}
,{"word": "c", "value":3.529}
,{"word": "a", "value":2.12993}
,{"word": "veloppement", "value":5.15933}
,{"word": "de", "value":0.428779}
,{"word": "l", "value":1.55233}
,{"word": "e", "value":2.29191}
,{"word": "intelligence", "value":5.03207}
,{"word": "artificielle", "value":5.88488}
,{"word": "octobre", "value":4.24326}
,{"word": "l", "value":1.55233}
,{"word": "inscription", "value":1.77898}
,{"word": "à", "value":0.325921}
,{"word": "cette", "value":4.11175}
,{"word": "journée", "value":13.6233}
,{"word": "est", "value":0.631034}
,{"word": "obligatoire", "value":3.06805}
,{"word": "avant", "value":3.82827}
,{"word": "le", "value":0.774863}
,{"word": "septembre", "value":4.36081}
,{"word": "sur", "value":0.782336}
,{"word": "le", "value":0.774863}
,{"word": "site", "value":2.95702}
,{"word": "http", "value":0.555942}
,{"word": "inscriptions", "value":4.9475}
,{"word": "afia", "value":20.1079}
,{"word": "asso", "value":5.29405}
,{"word": "fr", "value":0.340386}
,{"word": "au", "value":0.333685}
,{"word": "plaisir", "value":2.48682}
,{"word": "de", "value":0.428779}
,{"word": "vous", "value":1.89088}
,{"word": "rencontrer", "value":3.56912}
,{"word": "en", "value":0.80273}
,{"word": "cette", "value":4.11175}
,{"word": "occasion", "value":2.4262}
,{"word": "en", "value":0.80273}
,{"word": "en", "value":0.80273}
,{"word": "vous", "value":1.89088}
,{"word": "souhaitant", "value":3.57888}
,{"word": "une", "value":0.934198}
,{"word": "très", "value":2.06612}
,{"word": "bonne", "value":2.90553}
,{"word": "rentrée", "value":4.07672}
,{"word": "l", "value":1.55233}
,{"word": "accès", "value":4.15396}
,{"word": "y", "value":1.95195}
,{"word": "est", "value":0.631034}
,{"word": "gratuit", "value":4.25261}
,{"word": "pour", "value":0.939318}
,{"word": "les", "value":0.618975}
,{"word": "adhérents", "value":4.06072}
,{"word": "de", "value":0.428779}
,{"word": "l", "value":1.55233}
,{"word": "afia", "value":20.1079}
,{"word": "à", "value":0.325921}
,{"word": "jour", "value":2.88573}
,{"word": "de", "value":0.428779}
,{"word": "leur", "value":1.27727}
,{"word": "cotisation", "value":4.94575}
,{"word": "yves", "value":3.53102}
,{"word": "demazeau", "value":4.37521}
,{"word": "président", "value":2.49674}
,{"word": "de", "value":0.428779}
,{"word": "l", "value":1.55233}
,{"word": "afia", "value":20.1079}
]}
