{"text":1534,"subject":[
{"word": "offre", "value":2.40173}
,{"word": "de", "value":1.76665}
,{"word": "post", "value":3.30601}
,{"word": "doc", "value":3.84714}
,{"word": "à", "value":1.10465}
,{"word": "l", "value":2.11708}
,{"word": "ens", "value":7.10524}
,{"word": "de", "value":1.76665}
,{"word": "lyon", "value":3.57888}
,{"word": "analyse", "value":3.60873}
,{"word": "modélisation", "value":4.94575}
,{"word": "et", "value":1.51053}
,{"word": "simulation", "value":6.59441}
,{"word": "des", "value":2.22497}
,{"word": "déplacements", "value":7.10524}
,{"word": "en", "value":2.20989}
,{"word": "vélo", "value":7.5107}
,{"word": "libre", "value":7.10524}
,{"word": "service", "value":5.80596}
,{"word": "vls", "value":7.5107}
,{"word": "offre", "value":2.40173}
,{"word": "de", "value":1.76665}
,{"word": "post", "value":3.30601}
,{"word": "doc", "value":3.84714}
,{"word": "à", "value":1.10465}
,{"word": "l", "value":2.11708}
,{"word": "ens", "value":7.10524}
,{"word": "de", "value":1.76665}
,{"word": "lyon", "value":3.57888}
,{"word": "analyse", "value":3.60873}
,{"word": "modélisation", "value":4.94575}
,{"word": "et", "value":1.51053}
,{"word": "simulation", "value":6.59441}
,{"word": "des", "value":2.22497}
,{"word": "déplacements", "value":7.10524}
,{"word": "en", "value":2.20989}
,{"word": "vélo", "value":7.5107}
,{"word": "libre", "value":7.10524}
,{"word": "service", "value":5.80596}
,{"word": "vls", "value":7.5107}
],"content":[
{"word": "offre", "value":2.08575}
,{"word": "de", "value":1.00048}
,{"word": "post", "value":18.3162}
,{"word": "doc", "value":15.8999}
,{"word": "à", "value":0.814801}
,{"word": "l", "value":0.862406}
,{"word": "ens", "value":56.418}
,{"word": "de", "value":1.00048}
,{"word": "lyon", "value":41.3094}
,{"word": "laboratoire", "value":6.02214}
,{"word": "de", "value":1.00048}
,{"word": "physique", "value":27.9546}
,{"word": "équipe", "value":6.68607}
,{"word": "sisyphe", "value":45.0642}
,{"word": "signaux", "value":9.18587}
,{"word": "systèmes", "value":3.63251}
,{"word": "et", "value":1.51178}
,{"word": "physique", "value":27.9546}
,{"word": "offre", "value":2.08575}
,{"word": "de", "value":1.00048}
,{"word": "post", "value":18.3162}
,{"word": "doc", "value":15.8999}
,{"word": "à", "value":0.814801}
,{"word": "l", "value":0.862406}
,{"word": "ens", "value":56.418}
,{"word": "de", "value":1.00048}
,{"word": "lyon", "value":41.3094}
,{"word": "laboratoire", "value":6.02214}
,{"word": "de", "value":1.00048}
,{"word": "physique", "value":27.9546}
,{"word": "équipe", "value":6.68607}
,{"word": "sisyphe", "value":45.0642}
,{"word": "signaux", "value":9.18587}
,{"word": "systèmes", "value":3.63251}
,{"word": "et", "value":1.51178}
,{"word": "physique", "value":27.9546}
,{"word": "announcement", "value":5.4958}
,{"word": "in", "value":18.0359}
,{"word": "english", "value":3.23404}
,{"word": "at", "value":9.64335}
,{"word": "the", "value":50.0301}
,{"word": "end", "value":4.6485}
,{"word": "sujet", "value":1.8994}
,{"word": "analyse", "value":7.6922}
,{"word": "modélisation", "value":4.92422}
,{"word": "et", "value":1.51178}
,{"word": "simulation", "value":6.03293}
,{"word": "des", "value":1.42038}
,{"word": "déplacements", "value":11.0138}
,{"word": "en", "value":1.49078}
,{"word": "vélo", "value":42.6314}
,{"word": "libre", "value":5.83117}
,{"word": "service", "value":5.8413}
,{"word": "vls", "value":27.2702}
,{"word": "contexte", "value":1.61906}
,{"word": "dans", "value":0.559558}
,{"word": "le", "value":1.54973}
,{"word": "cadre", "value":2.44012}
,{"word": "d", "value":0.580757}
,{"word": "un", "value":1.11914}
,{"word": "projet", "value":4.79566}
,{"word": "anr", "value":8.70164}
,{"word": "sur", "value":0.782336}
,{"word": "les", "value":1.70218}
,{"word": "vélos", "value":6.41209}
,{"word": "en", "value":1.49078}
,{"word": "libre", "value":5.83117}
,{"word": "service", "value":5.8413}
,{"word": "vls", "value":27.2702}
,{"word": "automatisés", "value":5.90127}
,{"word": "tout", "value":1.77413}
,{"word": "particulièrement", "value":2.41084}
,{"word": "vélo", "value":42.6314}
,{"word": "v", "value":17.9934}
,{"word": "à", "value":0.814801}
,{"word": "lyon", "value":41.3094}
,{"word": "qui", "value":0.734767}
,{"word": "s", "value":0.714998}
,{"word": "intéresse", "value":3.43317}
,{"word": "à", "value":0.814801}
,{"word": "les", "value":1.70218}
,{"word": "analyser", "value":6.37314}
,{"word": "en", "value":1.49078}
,{"word": "tant", "value":8.74675}
,{"word": "que", "value":2.31943}
,{"word": "système", "value":4.04767}
,{"word": "socio", "value":7.85437}
,{"word": "technique", "value":2.69042}
,{"word": "innovant", "value":6.25794}
,{"word": "et", "value":1.51178}
,{"word": "à", "value":0.814801}
,{"word": "étudier", "value":3.23404}
,{"word": "leurs", "value":1.47882}
,{"word": "appropriations", "value":6.81756}
,{"word": "sociales", "value":4.94102}
,{"word": "par", "value":1.33527}
,{"word": "les", "value":1.70218}
,{"word": "utilisateurs", "value":2.26105}
,{"word": "l", "value":0.862406}
,{"word": "équipe", "value":6.68607}
,{"word": "sisyphe", "value":45.0642}
,{"word": "du", "value":0.911334}
,{"word": "laboratoire", "value":6.02214}
,{"word": "de", "value":1.00048}
,{"word": "physique", "value":27.9546}
,{"word": "de", "value":1.00048}
,{"word": "l", "value":0.862406}
,{"word": "ens", "value":56.418}
,{"word": "de", "value":1.00048}
,{"word": "lyon", "value":41.3094}
,{"word": "recrute", "value":3.5125}
,{"word": "un", "value":1.11914}
,{"word": "chercheur", "value":2.48027}
,{"word": "pour", "value":1.69077}
,{"word": "un", "value":1.11914}
,{"word": "contrat", "value":6.11271}
,{"word": "post", "value":18.3162}
,{"word": "doctoral", "value":7.66881}
,{"word": "de", "value":1.00048}
,{"word": "mois", "value":4.05597}
,{"word": "pouvant", "value":3.06805}
,{"word": "être", "value":1.83121}
,{"word": "étendu", "value":4.70734}
,{"word": "à", "value":0.814801}
,{"word": "mois", "value":4.05597}
,{"word": "recruté", "value":11.7402}
,{"word": "par", "value":1.33527}
,{"word": "l", "value":0.862406}
,{"word": "ens", "value":56.418}
,{"word": "de", "value":1.00048}
,{"word": "lyon", "value":41.3094}
,{"word": "le", "value":1.54973}
,{"word": "post", "value":18.3162}
,{"word": "doc", "value":15.8999}
,{"word": "travaillera", "value":8.98056}
,{"word": "de", "value":1.00048}
,{"word": "manière", "value":2.67046}
,{"word": "proche", "value":4.73812}
,{"word": "avec", "value":1.27094}
,{"word": "le", "value":1.54973}
,{"word": "liris", "value":12.1108}
,{"word": "insa", "value":2.85199}
,{"word": "de", "value":1.00048}
,{"word": "lyon", "value":41.3094}
,{"word": "pour", "value":1.69077}
,{"word": "des", "value":1.42038}
,{"word": "aspects", "value":2.21489}
,{"word": "de", "value":1.00048}
,{"word": "fouille", "value":1.46215}
,{"word": "de", "value":1.00048}
,{"word": "données", "value":4.30007}
,{"word": "et", "value":1.51178}
,{"word": "le", "value":1.54973}
,{"word": "let", "value":23.2238}
,{"word": "laboratoire", "value":6.02214}
,{"word": "d", "value":0.580757}
,{"word": "économie", "value":3.57888}
,{"word": "des", "value":1.42038}
,{"word": "transports", "value":6.86633}
,{"word": "pour", "value":1.69077}
,{"word": "les", "value":1.70218}
,{"word": "questions", "value":2.07045}
,{"word": "portant", "value":3.11626}
,{"word": "sur", "value":0.782336}
,{"word": "la", "value":0.760075}
,{"word": "mobilité", "value":3.30601}
,{"word": "et", "value":1.51178}
,{"word": "les", "value":1.70218}
,{"word": "transports", "value":6.86633}
,{"word": "partant", "value":5.31348}
,{"word": "de", "value":1.00048}
,{"word": "l", "value":0.862406}
,{"word": "analyse", "value":7.6922}
,{"word": "de", "value":1.00048}
,{"word": "la", "value":0.760075}
,{"word": "base", "value":4.00668}
,{"word": "de", "value":1.00048}
,{"word": "données", "value":4.30007}
,{"word": "de", "value":1.00048}
,{"word": "déplacements", "value":11.0138}
,{"word": "en", "value":1.49078}
,{"word": "vélo", "value":42.6314}
,{"word": "v", "value":17.9934}
,{"word": "dont", "value":1.94236}
,{"word": "nous", "value":1.71956}
,{"word": "disposons", "value":5.80596}
,{"word": "pour", "value":1.69077}
,{"word": "plusieurs", "value":1.83395}
,{"word": "années", "value":2.22244}
,{"word": "consécutives", "value":7.5107}
,{"word": "les", "value":1.70218}
,{"word": "objectifs", "value":2.29849}
,{"word": "principaux", "value":3.17341}
,{"word": "du", "value":0.911334}
,{"word": "projet", "value":4.79566}
,{"word": "post", "value":18.3162}
,{"word": "doctoral", "value":7.66881}
,{"word": "seront", "value":1.21084}
,{"word": "de", "value":1.00048}
,{"word": "caractériser", "value":4.37521}
,{"word": "de", "value":1.00048}
,{"word": "façon", "value":2.7789}
,{"word": "précise", "value":4.39719}
,{"word": "les", "value":1.70218}
,{"word": "déplacements", "value":11.0138}
,{"word": "effectués", "value":4.76986}
,{"word": "tant", "value":8.74675}
,{"word": "localement", "value":5.71894}
,{"word": "que", "value":2.31943}
,{"word": "globalement", "value":5.06836}
,{"word": "d", "value":0.580757}
,{"word": "apporter", "value":3.57888}
,{"word": "des", "value":1.42038}
,{"word": "approches", "value":3.70593}
,{"word": "innovantes", "value":3.3135}
,{"word": "pour", "value":1.69077}
,{"word": "analyser", "value":6.37314}
,{"word": "le", "value":1.54973}
,{"word": "système", "value":4.04767}
,{"word": "en", "value":1.49078}
,{"word": "particulier", "value":1.97929}
,{"word": "en", "value":1.49078}
,{"word": "tant", "value":8.74675}
,{"word": "que", "value":2.31943}
,{"word": "réseau", "value":2.91558}
,{"word": "dynamique", "value":2.60543}
,{"word": "et", "value":1.51178}
,{"word": "de", "value":1.00048}
,{"word": "proposer", "value":2.37491}
,{"word": "des", "value":1.42038}
,{"word": "modèles", "value":1.57713}
,{"word": "ou", "value":3.07317}
,{"word": "des", "value":1.42038}
,{"word": "approches", "value":3.70593}
,{"word": "pour", "value":1.69077}
,{"word": "simuler", "value":4.94575}
,{"word": "au", "value":0.667371}
,{"word": "mieux", "value":2.97274}
,{"word": "le", "value":1.54973}
,{"word": "comportement", "value":3.52172}
,{"word": "d", "value":0.580757}
,{"word": "un", "value":1.11914}
,{"word": "vls", "value":27.2702}
,{"word": "et", "value":1.51178}
,{"word": "les", "value":1.70218}
,{"word": "impacts", "value":4.56627}
,{"word": "de", "value":1.00048}
,{"word": "différents", "value":1.85297}
,{"word": "changements", "value":3.89979}
,{"word": "dans", "value":0.559558}
,{"word": "la", "value":0.760075}
,{"word": "ville", "value":3.38357}
,{"word": "sur", "value":0.782336}
,{"word": "son", "value":1.72842}
,{"word": "fonctionnement", "value":3.88636}
,{"word": "cadre", "value":2.44012}
,{"word": "de", "value":1.00048}
,{"word": "travail", "value":3.29699}
,{"word": "la", "value":0.760075}
,{"word": "personne", "value":2.43241}
,{"word": "recrutée", "value":3.60873}
,{"word": "travaillera", "value":8.98056}
,{"word": "à", "value":0.814801}
,{"word": "lyon", "value":41.3094}
,{"word": "au", "value":0.667371}
,{"word": "sein", "value":1.79039}
,{"word": "du", "value":0.911334}
,{"word": "projet", "value":4.79566}
,{"word": "anr", "value":8.70164}
,{"word": "vel", "value":7.5107}
,{"word": "innov", "value":5.6389}
,{"word": "associant", "value":4.39719}
,{"word": "les", "value":1.70218}
,{"word": "laboratoire", "value":6.02214}
,{"word": "de", "value":1.00048}
,{"word": "physique", "value":27.9546}
,{"word": "sociologie", "value":3.24802}
,{"word": "et", "value":1.51178}
,{"word": "géographie", "value":3.99916}
,{"word": "de", "value":1.00048}
,{"word": "l", "value":0.862406}
,{"word": "ens", "value":56.418}
,{"word": "de", "value":1.00048}
,{"word": "lyon", "value":41.3094}
,{"word": "l", "value":0.862406}
,{"word": "ixxi", "value":6.81756}
,{"word": "le", "value":1.54973}
,{"word": "liris", "value":12.1108}
,{"word": "le", "value":1.54973}
,{"word": "let", "value":23.2238}
,{"word": "et", "value":1.51178}
,{"word": "le", "value":1.54973}
,{"word": "polytech", "value":6.90052}
,{"word": "montreal", "value":12.0133}
,{"word": "profil", "value":2.03424}
,{"word": "des", "value":1.42038}
,{"word": "candidats", "value":2.67046}
,{"word": "les", "value":1.70218}
,{"word": "compétences", "value":4.31769}
,{"word": "attendues", "value":6.18373}
,{"word": "pour", "value":1.69077}
,{"word": "le", "value":1.54973}
,{"word": "ou", "value":3.07317}
,{"word": "la", "value":0.760075}
,{"word": "candidat", "value":6.73628}
,{"word": "e", "value":5.72977}
,{"word": "sont", "value":1.18699}
,{"word": "en", "value":1.49078}
,{"word": "analyse", "value":7.6922}
,{"word": "des", "value":1.42038}
,{"word": "données", "value":4.30007}
,{"word": "avec", "value":1.27094}
,{"word": "une", "value":0.622799}
,{"word": "formation", "value":2.33173}
,{"word": "en", "value":1.49078}
,{"word": "traitement", "value":2.64078}
,{"word": "du", "value":0.911334}
,{"word": "signal", "value":12.8755}
,{"word": "ou", "value":3.07317}
,{"word": "informatique", "value":0.787473}
,{"word": "un", "value":1.11914}
,{"word": "intérêt", "value":2.24801}
,{"word": "pour", "value":1.69077}
,{"word": "l", "value":0.862406}
,{"word": "étude", "value":2.39271}
,{"word": "de", "value":1.00048}
,{"word": "données", "value":4.30007}
,{"word": "liées", "value":2.32053}
,{"word": "aux", "value":0.616034}
,{"word": "sciences", "value":1.34634}
,{"word": "sociales", "value":4.94102}
,{"word": "est", "value":0.631034}
,{"word": "nécessaire", "value":2.89558}
,{"word": "des", "value":1.42038}
,{"word": "compétences", "value":4.31769}
,{"word": "en", "value":1.49078}
,{"word": "modélisation", "value":4.92422}
,{"word": "stochastique", "value":5.71894}
,{"word": "en", "value":1.49078}
,{"word": "analyse", "value":7.6922}
,{"word": "des", "value":1.42038}
,{"word": "réseaux", "value":1.54584}
,{"word": "complexes", "value":2.26105}
,{"word": "et", "value":1.51178}
,{"word": "ou", "value":3.07317}
,{"word": "en", "value":1.49078}
,{"word": "systèmes", "value":3.63251}
,{"word": "multi", "value":3.79151}
,{"word": "agents", "value":2.53053}
,{"word": "sont", "value":1.18699}
,{"word": "attendues", "value":6.18373}
,{"word": "le", "value":1.54973}
,{"word": "ou", "value":3.07317}
,{"word": "la", "value":0.760075}
,{"word": "candidat", "value":6.73628}
,{"word": "e", "value":5.72977}
,{"word": "recruté", "value":11.7402}
,{"word": "e", "value":5.72977}
,{"word": "devra", "value":4.62995}
,{"word": "une", "value":0.622799}
,{"word": "véritable", "value":4.94575}
,{"word": "motivation", "value":4.28013}
,{"word": "pour", "value":1.69077}
,{"word": "le", "value":1.54973}
,{"word": "travail", "value":3.29699}
,{"word": "interdisciplinaire", "value":3.19991}
,{"word": "le", "value":1.54973}
,{"word": "ou", "value":3.07317}
,{"word": "la", "value":0.760075}
,{"word": "candidat", "value":6.73628}
,{"word": "e", "value":5.72977}
,{"word": "recruté", "value":11.7402}
,{"word": "e", "value":5.72977}
,{"word": "devra", "value":4.62995}
,{"word": "aussi", "value":1.58378}
,{"word": "contribuer", "value":3.3135}
,{"word": "à", "value":0.814801}
,{"word": "la", "value":0.760075}
,{"word": "gestion", "value":1.38821}
,{"word": "mise", "value":2.02798}
,{"word": "en", "value":1.49078}
,{"word": "forme", "value":1.79697}
,{"word": "et", "value":1.51178}
,{"word": "analyse", "value":7.6922}
,{"word": "de", "value":1.00048}
,{"word": "la", "value":0.760075}
,{"word": "base", "value":4.00668}
,{"word": "de", "value":1.00048}
,{"word": "données", "value":4.30007}
,{"word": "le", "value":1.54973}
,{"word": "principal", "value":3.54041}
,{"word": "objectif", "value":1.36545}
,{"word": "est", "value":0.631034}
,{"word": "cependant", "value":3.09186}
,{"word": "de", "value":1.00048}
,{"word": "participer", "value":2.51012}
,{"word": "à", "value":0.814801}
,{"word": "des", "value":1.42038}
,{"word": "travaux", "value":1.26073}
,{"word": "d", "value":0.580757}
,{"word": "analyse", "value":7.6922}
,{"word": "de", "value":1.00048}
,{"word": "traitement", "value":2.64078}
,{"word": "et", "value":1.51178}
,{"word": "de", "value":1.00048}
,{"word": "modélisation", "value":4.92422}
,{"word": "des", "value":1.42038}
,{"word": "données", "value":4.30007}
,{"word": "vls", "value":27.2702}
,{"word": "à", "value":0.814801}
,{"word": "l", "value":0.862406}
,{"word": "aide", "value":2.0197}
,{"word": "d", "value":0.580757}
,{"word": "outils", "value":1.46215}
,{"word": "innovants", "value":3.49432}
,{"word": "début", "value":2.47051}
,{"word": "du", "value":0.911334}
,{"word": "contrat", "value":6.11271}
,{"word": "entre", "value":1.10962}
,{"word": "maintenant", "value":3.19991}
,{"word": "et", "value":1.51178}
,{"word": "janvier", "value":1.83738}
,{"word": "contacts", "value":4.5221}
,{"word": "et", "value":1.51178}
,{"word": "informations", "value":2.48132}
,{"word": "supplémentaires", "value":10.1367}
,{"word": "les", "value":1.70218}
,{"word": "candidatures", "value":2.59438}
,{"word": "cv", "value":4.09799}
,{"word": "articles", "value":2.64899}
,{"word": "sélectionnés", "value":3.32105}
,{"word": "pertinents", "value":4.04497}
,{"word": "et", "value":1.51178}
,{"word": "d", "value":0.580757}
,{"word": "éventuelles", "value":4.14341}
,{"word": "lettres", "value":3.40806}
,{"word": "de", "value":1.00048}
,{"word": "recommandations", "value":3.34404}
,{"word": "doivent", "value":1.7645}
,{"word": "être", "value":1.83121}
,{"word": "envoyées", "value":3.36757}
,{"word": "par", "value":1.33527}
,{"word": "mail", "value":2.09017}
,{"word": "à", "value":0.814801}
,{"word": "pierre", "value":3.92715}
,{"word": "borgnat", "value":15.0214}
,{"word": "ens", "value":56.418}
,{"word": "lyon", "value":41.3094}
,{"word": "fr", "value":1.36154}
,{"word": "patrice", "value":7.36413}
,{"word": "abry", "value":15.0214}
,{"word": "ens", "value":56.418}
,{"word": "lyon", "value":41.3094}
,{"word": "fr", "value":1.36154}
,{"word": "et", "value":1.51178}
,{"word": "pablo", "value":13.1888}
,{"word": "jensen", "value":15.0214}
,{"word": "ens", "value":56.418}
,{"word": "lyon", "value":41.3094}
,{"word": "fr", "value":1.36154}
,{"word": "informations", "value":2.48132}
,{"word": "supplémentaires", "value":10.1367}
,{"word": "en", "value":1.49078}
,{"word": "nous", "value":1.71956}
,{"word": "contactant", "value":7.5107}
,{"word": "page", "value":6.0715}
,{"word": "web", "value":0.906083}
,{"word": "de", "value":1.00048}
,{"word": "l", "value":0.862406}
,{"word": "équipe", "value":6.68607}
,{"word": "sisyphe", "value":45.0642}
,{"word": "http", "value":0.555942}
,{"word": "www", "value":1.19991}
,{"word": "ens", "value":56.418}
,{"word": "lyon", "value":41.3094}
,{"word": "fr", "value":1.36154}
,{"word": "physique", "value":27.9546}
,{"word": "index", "value":5.21828}
,{"word": "php", "value":4.41978}
,{"word": "page", "value":6.0715}
,{"word": "equipe", "value":5.8617}
,{"word": "post", "value":18.3162}
,{"word": "doc", "value":15.8999}
,{"word": "position", "value":6.37314}
,{"word": "at", "value":9.64335}
,{"word": "ens", "value":56.418}
,{"word": "de", "value":1.00048}
,{"word": "lyon", "value":41.3094}
,{"word": "laboratoire", "value":6.02214}
,{"word": "de", "value":1.00048}
,{"word": "physique", "value":27.9546}
,{"word": "équipe", "value":6.68607}
,{"word": "sisyphe", "value":45.0642}
,{"word": "signaux", "value":9.18587}
,{"word": "systèmes", "value":3.63251}
,{"word": "et", "value":1.51178}
,{"word": "physique", "value":27.9546}
,{"word": "subject", "value":4.31203}
,{"word": "analysis", "value":15.2528}
,{"word": "modeling", "value":17.9611}
,{"word": "and", "value":21.6778}
,{"word": "simulation", "value":6.03293}
,{"word": "of", "value":23.3619}
,{"word": "bicycle", "value":15.0214}
,{"word": "sharing", "value":9.81603}
,{"word": "systems", "value":11.427}
,{"word": "bss", "value":45.0642}
,{"word": "context", "value":3.92719}
,{"word": "as", "value":9.61992}
,{"word": "part", "value":2.40779}
,{"word": "of", "value":23.3619}
,{"word": "an", "value":4.84005}
,{"word": "anr", "value":8.70164}
,{"word": "project", "value":3.28387}
,{"word": "about", "value":7.54607}
,{"word": "the", "value":50.0301}
,{"word": "use", "value":3.71522}
,{"word": "of", "value":23.3619}
,{"word": "bicycle", "value":15.0214}
,{"word": "sharing", "value":9.81603}
,{"word": "systems", "value":11.427}
,{"word": "or", "value":13.7641}
,{"word": "bss", "value":45.0642}
,{"word": "especially", "value":10.627}
,{"word": "vélo", "value":42.6314}
,{"word": "v", "value":17.9934}
,{"word": "in", "value":18.0359}
,{"word": "lyon", "value":41.3094}
,{"word": "to", "value":26.8833}
,{"word": "characterize", "value":13.6351}
,{"word": "it", "value":3.00535}
,{"word": "as", "value":9.61992}
,{"word": "innovative", "value":10.8625}
,{"word": "socio", "value":7.85437}
,{"word": "technical", "value":4.25261}
,{"word": "systems", "value":11.427}
,{"word": "and", "value":21.6778}
,{"word": "complement", "value":7.10524}
,{"word": "the", "value":50.0301}
,{"word": "studies", "value":8.50522}
,{"word": "by", "value":8.43067}
,{"word": "a", "value":6.3898}
,{"word": "social", "value":5.15246}
,{"word": "perspective", "value":3.86005}
,{"word": "the", "value":50.0301}
,{"word": "group", "value":6.98864}
,{"word": "of", "value":23.3619}
,{"word": "signal", "value":12.8755}
,{"word": "processing", "value":10.2491}
,{"word": "sisyphe", "value":45.0642}
,{"word": "from", "value":5.43811}
,{"word": "the", "value":50.0301}
,{"word": "laboratory", "value":7.85437}
,{"word": "of", "value":23.3619}
,{"word": "physics", "value":12.0133}
,{"word": "of", "value":23.3619}
,{"word": "the", "value":50.0301}
,{"word": "ens", "value":56.418}
,{"word": "lyon", "value":41.3094}
,{"word": "hire", "value":7.5107}
,{"word": "a", "value":6.3898}
,{"word": "collaborator", "value":7.5107}
,{"word": "with", "value":17.3735}
,{"word": "a", "value":6.3898}
,{"word": "phd", "value":3.07989}
,{"word": "for", "value":5.90832}
,{"word": "a", "value":6.3898}
,{"word": "duration", "value":5.20812}
,{"word": "of", "value":23.3619}
,{"word": "months", "value":5.0258}
,{"word": "possibly", "value":6.25794}
,{"word": "extended", "value":4.51497}
,{"word": "to", "value":26.8833}
,{"word": "he", "value":4.56627}
,{"word": "she", "value":5.80596}
,{"word": "will", "value":15.5199}
,{"word": "work", "value":10.8567}
,{"word": "also", "value":11.5032}
,{"word": "with", "value":17.3735}
,{"word": "the", "value":50.0301}
,{"word": "laboratories", "value":5.80596}
,{"word": "liris", "value":12.1108}
,{"word": "and", "value":21.6778}
,{"word": "let", "value":23.2238}
,{"word": "on", "value":1.6585}
,{"word": "lyon", "value":41.3094}
,{"word": "from", "value":5.43811}
,{"word": "the", "value":50.0301}
,{"word": "analysis", "value":15.2528}
,{"word": "of", "value":23.3619}
,{"word": "a", "value":6.3898}
,{"word": "database", "value":9.35498}
,{"word": "recording", "value":7.5107}
,{"word": "all", "value":3.78501}
,{"word": "the", "value":50.0301}
,{"word": "trips", "value":21.3157}
,{"word": "made", "value":5.6389}
,{"word": "in", "value":18.0359}
,{"word": "lyon", "value":41.3094}
,{"word": "using", "value":3.54041}
,{"word": "bss", "value":45.0642}
,{"word": "vélo", "value":42.6314}
,{"word": "v", "value":17.9934}
,{"word": "during", "value":4.46618}
,{"word": "several", "value":4.62033}
,{"word": "years", "value":4.56627}
,{"word": "the", "value":50.0301}
,{"word": "main", "value":8.15343}
,{"word": "objectives", "value":6.12441}
,{"word": "are", "value":6.10112}
,{"word": "to", "value":26.8833}
,{"word": "precisely", "value":7.10524}
,{"word": "characterize", "value":13.6351}
,{"word": "the", "value":50.0301}
,{"word": "trips", "value":21.3157}
,{"word": "both", "value":4.41966}
,{"word": "locally", "value":7.10524}
,{"word": "and", "value":21.6778}
,{"word": "globally", "value":7.5107}
,{"word": "to", "value":26.8833}
,{"word": "propose", "value":4.96053}
,{"word": "new", "value":6.67263}
,{"word": "approaches", "value":11.3914}
,{"word": "to", "value":26.8833}
,{"word": "analyse", "value":7.6922}
,{"word": "bss", "value":45.0642}
,{"word": "especially", "value":10.627}
,{"word": "in", "value":18.0359}
,{"word": "their", "value":3.71522}
,{"word": "modeling", "value":17.9611}
,{"word": "as", "value":9.61992}
,{"word": "complex", "value":8.83932}
,{"word": "networks", "value":7.21746}
,{"word": "and", "value":21.6778}
,{"word": "to", "value":26.8833}
,{"word": "propose", "value":4.96053}
,{"word": "new", "value":6.67263}
,{"word": "models", "value":3.8094}
,{"word": "or", "value":13.7641}
,{"word": "simulations", "value":3.7495}
,{"word": "approaches", "value":11.3914}
,{"word": "to", "value":26.8833}
,{"word": "understand", "value":5.43126}
,{"word": "how", "value":4.25261}
,{"word": "bss", "value":45.0642}
,{"word": "react", "value":6.81756}
,{"word": "to", "value":26.8833}
,{"word": "changes", "value":5.4958}
,{"word": "in", "value":18.0359}
,{"word": "a", "value":6.3898}
,{"word": "city", "value":5.37064}
,{"word": "location", "value":4.67749}
,{"word": "the", "value":50.0301}
,{"word": "work", "value":10.8567}
,{"word": "will", "value":15.5199}
,{"word": "de", "value":1.00048}
,{"word": "done", "value":5.56479}
,{"word": "at", "value":9.64335}
,{"word": "the", "value":50.0301}
,{"word": "ens", "value":56.418}
,{"word": "lyon", "value":41.3094}
,{"word": "france", "value":1.07616}
,{"word": "the", "value":50.0301}
,{"word": "post", "value":18.3162}
,{"word": "doc", "value":15.8999}
,{"word": "will", "value":15.5199}
,{"word": "be", "value":5.69453}
,{"word": "in", "value":18.0359}
,{"word": "the", "value":50.0301}
,{"word": "laboratory", "value":7.85437}
,{"word": "of", "value":23.3619}
,{"word": "physics", "value":12.0133}
,{"word": "and", "value":21.6778}
,{"word": "will", "value":15.5199}
,{"word": "also", "value":11.5032}
,{"word": "collaborate", "value":6.81756}
,{"word": "with", "value":17.3735}
,{"word": "the", "value":50.0301}
,{"word": "departments", "value":7.10524}
,{"word": "of", "value":23.3619}
,{"word": "sociology", "value":5.90127}
,{"word": "or", "value":13.7641}
,{"word": "geography", "value":7.10524}
,{"word": "the", "value":50.0301}
,{"word": "liris", "value":12.1108}
,{"word": "and", "value":21.6778}
,{"word": "the", "value":50.0301}
,{"word": "let", "value":23.2238}
,{"word": "in", "value":18.0359}
,{"word": "lyon", "value":41.3094}
,{"word": "and", "value":21.6778}
,{"word": "polytech", "value":6.90052}
,{"word": "montreal", "value":12.0133}
,{"word": "applicants", "value":17.4179}
,{"word": "profile", "value":4.51497}
,{"word": "the", "value":50.0301}
,{"word": "applicants", "value":17.4179}
,{"word": "should", "value":11.2836}
,{"word": "have", "value":6.68808}
,{"word": "a", "value":6.3898}
,{"word": "good", "value":4.94575}
,{"word": "competences", "value":11.4379}
,{"word": "in", "value":18.0359}
,{"word": "data", "value":3.98586}
,{"word": "analysis", "value":15.2528}
,{"word": "with", "value":17.3735}
,{"word": "a", "value":6.3898}
,{"word": "background", "value":6.41209}
,{"word": "in", "value":18.0359}
,{"word": "signal", "value":12.8755}
,{"word": "processing", "value":10.2491}
,{"word": "or", "value":13.7641}
,{"word": "computer", "value":2.76143}
,{"word": "science", "value":3.99455}
,{"word": "an", "value":4.84005}
,{"word": "interest", "value":4.83656}
,{"word": "for", "value":5.90832}
,{"word": "the", "value":50.0301}
,{"word": "study", "value":8.15343}
,{"word": "of", "value":23.3619}
,{"word": "social", "value":5.15246}
,{"word": "science", "value":3.99455}
,{"word": "data", "value":3.98586}
,{"word": "is", "value":5.47158}
,{"word": "required", "value":4.59293}
,{"word": "competences", "value":11.4379}
,{"word": "in", "value":18.0359}
,{"word": "stochastic", "value":7.5107}
,{"word": "modeling", "value":17.9611}
,{"word": "complex", "value":8.83932}
,{"word": "networks", "value":7.21746}
,{"word": "study", "value":8.15343}
,{"word": "and", "value":21.6778}
,{"word": "or", "value":13.7641}
,{"word": "multi", "value":3.79151}
,{"word": "agent", "value":3.47646}
,{"word": "systems", "value":11.427}
,{"word": "are", "value":6.10112}
,{"word": "expected", "value":5.4958}
,{"word": "applicants", "value":17.4179}
,{"word": "should", "value":11.2836}
,{"word": "have", "value":6.68808}
,{"word": "a", "value":6.3898}
,{"word": "real", "value":4.31203}
,{"word": "motivation", "value":4.28013}
,{"word": "for", "value":5.90832}
,{"word": "inter", "value":3.95536}
,{"word": "disciplinary", "value":6.41209}
,{"word": "studies", "value":8.50522}
,{"word": "the", "value":50.0301}
,{"word": "post", "value":18.3162}
,{"word": "doc", "value":15.8999}
,{"word": "will", "value":15.5199}
,{"word": "also", "value":11.5032}
,{"word": "contribute", "value":10.8625}
,{"word": "to", "value":26.8833}
,{"word": "the", "value":50.0301}
,{"word": "organization", "value":4.59293}
,{"word": "maintenance", "value":3.8344}
,{"word": "and", "value":21.6778}
,{"word": "analysis", "value":15.2528}
,{"word": "procedures", "value":6.12441}
,{"word": "of", "value":23.3619}
,{"word": "the", "value":50.0301}
,{"word": "database", "value":9.35498}
,{"word": "of", "value":23.3619}
,{"word": "vélo", "value":42.6314}
,{"word": "v", "value":17.9934}
,{"word": "trips", "value":21.3157}
,{"word": "however", "value":4.87165}
,{"word": "the", "value":50.0301}
,{"word": "main", "value":8.15343}
,{"word": "objective", "value":5.37064}
,{"word": "is", "value":5.47158}
,{"word": "to", "value":26.8833}
,{"word": "contribute", "value":10.8625}
,{"word": "with", "value":17.3735}
,{"word": "innovative", "value":10.8625}
,{"word": "approaches", "value":11.3914}
,{"word": "to", "value":26.8833}
,{"word": "the", "value":50.0301}
,{"word": "analysis", "value":15.2528}
,{"word": "processing", "value":10.2491}
,{"word": "and", "value":21.6778}
,{"word": "modeling", "value":17.9611}
,{"word": "of", "value":23.3619}
,{"word": "bss", "value":45.0642}
,{"word": "data", "value":3.98586}
,{"word": "position", "value":6.37314}
,{"word": "can", "value":3.44168}
,{"word": "begin", "value":5.71894}
,{"word": "immediately", "value":5.43126}
,{"word": "up", "value":4.09298}
,{"word": "to", "value":26.8833}
,{"word": "janauary", "value":7.5107}
,{"word": "contacts", "value":4.5221}
,{"word": "and", "value":21.6778}
,{"word": "additional", "value":5.4958}
,{"word": "information", "value":1.54866}
,{"word": "applications", "value":1.26266}
,{"word": "should", "value":11.2836}
,{"word": "be", "value":5.69453}
,{"word": "sent", "value":4.56627}
,{"word": "by", "value":8.43067}
,{"word": "email", "value":2.48682}
,{"word": "with", "value":17.3735}
,{"word": "cv", "value":4.09799}
,{"word": "selected", "value":4.98498}
,{"word": "articles", "value":2.64899}
,{"word": "and", "value":21.6778}
,{"word": "if", "value":3.58873}
,{"word": "relevant", "value":3.2912}
,{"word": "recommendation", "value":5.31348}
,{"word": "letter", "value":4.73812}
,{"word": "at", "value":9.64335}
,{"word": "pierre", "value":3.92715}
,{"word": "borgnat", "value":15.0214}
,{"word": "ens", "value":56.418}
,{"word": "lyon", "value":41.3094}
,{"word": "fr", "value":1.36154}
,{"word": "patrice", "value":7.36413}
,{"word": "abry", "value":15.0214}
,{"word": "ens", "value":56.418}
,{"word": "lyon", "value":41.3094}
,{"word": "fr", "value":1.36154}
,{"word": "and", "value":21.6778}
,{"word": "pablo", "value":13.1888}
,{"word": "jensen", "value":15.0214}
,{"word": "ens", "value":56.418}
,{"word": "lyon", "value":41.3094}
,{"word": "fr", "value":1.36154}
,{"word": "more", "value":3.88636}
,{"word": "information", "value":1.54866}
,{"word": "about", "value":7.54607}
,{"word": "the", "value":50.0301}
,{"word": "intended", "value":5.06836}
,{"word": "work", "value":10.8567}
,{"word": "by", "value":8.43067}
,{"word": "contacting", "value":7.5107}
,{"word": "us", "value":4.29183}
,{"word": "webpage", "value":6.12441}
,{"word": "of", "value":23.3619}
,{"word": "the", "value":50.0301}
,{"word": "sisyphe", "value":45.0642}
,{"word": "group", "value":6.98864}
,{"word": "http", "value":0.555942}
,{"word": "www", "value":1.19991}
,{"word": "ens", "value":56.418}
,{"word": "lyon", "value":41.3094}
,{"word": "fr", "value":1.36154}
,{"word": "physique", "value":27.9546}
,{"word": "index", "value":5.21828}
,{"word": "php", "value":4.41978}
,{"word": "page", "value":6.0715}
,{"word": "equipe", "value":5.8617}
]}
