{"text":2941,"subject":[
{"word": "journée", "value":3.09791}
,{"word": "thématique", "value":4.87165}
,{"word": "questionner", "value":7.5107}
,{"word": "les", "value":3.02207}
,{"word": "humanités", "value":4.51497}
,{"word": "numériques", "value":4.25261}
,{"word": "perspectives", "value":6.12441}
,{"word": "croisées", "value":7.5107}
,{"word": "cergy", "value":6.81756}
,{"word": "pontoise", "value":6.81756}
,{"word": "journée", "value":3.09791}
,{"word": "thématique", "value":4.87165}
,{"word": "questionner", "value":7.5107}
,{"word": "les", "value":3.02207}
,{"word": "humanités", "value":4.51497}
,{"word": "numériques", "value":4.25261}
,{"word": "perspectives", "value":6.12441}
,{"word": "croisées", "value":7.5107}
,{"word": "cergy", "value":6.81756}
,{"word": "pontoise", "value":6.81756}
],"content":[
{"word": "cher", "value":3.79713}
,{"word": "e", "value":1.14595}
,{"word": "s", "value":0.714998}
,{"word": "collègues", "value":2.71491}
,{"word": "cher", "value":3.79713}
,{"word": "e", "value":1.14595}
,{"word": "s", "value":0.714998}
,{"word": "collègues", "value":2.71491}
,{"word": "j", "value":2.36612}
,{"word": "ai", "value":3.23404}
,{"word": "le", "value":0.664168}
,{"word": "plaisir", "value":4.97365}
,{"word": "de", "value":0.686046}
,{"word": "vous", "value":4.7272}
,{"word": "inviter", "value":3.52172}
,{"word": "à", "value":0.651841}
,{"word": "la", "value":0.760075}
,{"word": "journée", "value":11.6771}
,{"word": "thématique", "value":2.25061}
,{"word": "intitulée", "value":3.70404}
,{"word": "questionner", "value":17.4179}
,{"word": "les", "value":0.773718}
,{"word": "humanités", "value":13.5343}
,{"word": "numériques", "value":13.3803}
,{"word": "perspectives", "value":12.1335}
,{"word": "croisées", "value":13.6351}
,{"word": "de", "value":0.686046}
,{"word": "la", "value":0.760075}
,{"word": "collecte", "value":10.4561}
,{"word": "des", "value":1.18365}
,{"word": "données", "value":1.43336}
,{"word": "sociales", "value":7.41153}
,{"word": "ou", "value":1.53658}
,{"word": "des", "value":1.18365}
,{"word": "corpus", "value":9.83059}
,{"word": "numériques", "value":13.3803}
,{"word": "à", "value":0.651841}
,{"word": "l", "value":0.862406}
,{"word": "émergence", "value":7.45303}
,{"word": "du", "value":1.27587}
,{"word": "sens", "value":8.68675}
,{"word": "organisée", "value":2.45128}
,{"word": "à", "value":0.651841}
,{"word": "cergy", "value":46.7787}
,{"word": "pontoise", "value":36.1198}
,{"word": "le", "value":0.664168}
,{"word": "avril", "value":3.66106}
,{"word": "si", "value":1.75655}
,{"word": "vous", "value":4.7272}
,{"word": "souhaitez", "value":4.09298}
,{"word": "assister", "value":3.55946}
,{"word": "à", "value":0.651841}
,{"word": "cette", "value":0.822349}
,{"word": "journée", "value":11.6771}
,{"word": "la", "value":0.760075}
,{"word": "participation", "value":2.14007}
,{"word": "est", "value":0.315517}
,{"word": "gratuite", "value":2.69446}
,{"word": "toutefois", "value":3.7495}
,{"word": "dans", "value":0.559558}
,{"word": "un", "value":0.671483}
,{"word": "souci", "value":5.80596}
,{"word": "d", "value":0.248896}
,{"word": "organisation", "value":1.49821}
,{"word": "veuillez", "value":2.45128}
,{"word": "vous", "value":4.7272}
,{"word": "inscrire", "value":2.82857}
,{"word": "auprès", "value":2.93599}
,{"word": "de", "value":0.686046}
,{"word": "l", "value":0.862406}
,{"word": "organisateur", "value":5.20812}
,{"word": "de", "value":0.686046}
,{"word": "la", "value":0.760075}
,{"word": "journée", "value":11.6771}
,{"word": "julien", "value":20.1109}
,{"word": "longhi", "value":29.0298}
,{"word": "par", "value":1.78036}
,{"word": "mail", "value":2.09017}
,{"word": "à", "value":0.651841}
,{"word": "l", "value":0.862406}
,{"word": "adresse", "value":3.93496}
,{"word": "julien", "value":20.1109}
,{"word": "longhi", "value":29.0298}
,{"word": "u", "value":8.45807}
,{"word": "cergy", "value":46.7787}
,{"word": "fr", "value":0.680772}
,{"word": "je", "value":2.90055}
,{"word": "vous", "value":4.7272}
,{"word": "prie", "value":5.15933}
,{"word": "de", "value":0.686046}
,{"word": "trouver", "value":2.81936}
,{"word": "ci", "value":1.6163}
,{"word": "dessous", "value":2.63933}
,{"word": "le", "value":0.664168}
,{"word": "programme", "value":1.16244}
,{"word": "de", "value":0.686046}
,{"word": "la", "value":0.760075}
,{"word": "journée", "value":11.6771}
,{"word": "ainsi", "value":1.31834}
,{"word": "que", "value":0.773144}
,{"word": "des", "value":1.18365}
,{"word": "informations", "value":2.48132}
,{"word": "concernant", "value":2.9835}
,{"word": "l", "value":0.862406}
,{"word": "accès", "value":4.15396}
,{"word": "informations", "value":2.48132}
,{"word": "disponibles", "value":2.14707}
,{"word": "également", "value":1.59316}
,{"word": "à", "value":0.651841}
,{"word": "l", "value":0.862406}
,{"word": "adresse", "value":3.93496}
,{"word": "http", "value":0.555942}
,{"word": "www", "value":1.19991}
,{"word": "u", "value":8.45807}
,{"word": "cergy", "value":46.7787}
,{"word": "fr", "value":0.680772}
,{"word": "fr", "value":0.680772}
,{"word": "laboratoires", "value":2.9781}
,{"word": "labo", "value":5.25941}
,{"word": "crtf", "value":12.2488}
,{"word": "actualite", "value":6.41209}
,{"word": "projets", "value":2.0748}
,{"word": "questionner", "value":17.4179}
,{"word": "les", "value":0.773718}
,{"word": "humanites", "value":5.71894}
,{"word": "numeriques", "value":9.81603}
,{"word": "perspectives", "value":12.1335}
,{"word": "croisees", "value":7.10524}
,{"word": "de", "value":0.686046}
,{"word": "la", "value":0.760075}
,{"word": "collecte", "value":10.4561}
,{"word": "des", "value":1.18365}
,{"word": "donnees", "value":4.49028}
,{"word": "sociales", "value":7.41153}
,{"word": "ou", "value":1.53658}
,{"word": "des", "value":1.18365}
,{"word": "corpus", "value":9.83059}
,{"word": "numeriques", "value":9.81603}
,{"word": "a", "value":0.709977}
,{"word": "l", "value":0.862406}
,{"word": "emergence", "value":5.56479}
,{"word": "du", "value":1.27587}
,{"word": "sens", "value":8.68675}
,{"word": "html", "value":2.38972}
,{"word": "au", "value":0.333685}
,{"word": "plaisir", "value":4.97365}
,{"word": "de", "value":0.686046}
,{"word": "vous", "value":4.7272}
,{"word": "voir", "value":2.3067}
,{"word": "amicalement", "value":4.98498}
,{"word": "claudia", "value":9.81603}
,{"word": "marinica", "value":10.8625}
,{"word": "laboratoire", "value":1.20443}
,{"word": "etis", "value":15.9404}
,{"word": "ucp", "value":16.6944}
,{"word": "ensea", "value":10.5188}
,{"word": "cnrs", "value":6.33754}
,{"word": "iut", "value":7.64358}
,{"word": "de", "value":0.686046}
,{"word": "cergy", "value":46.7787}
,{"word": "pontoise", "value":36.1198}
,{"word": "site", "value":0.985675}
,{"word": "sarcelles", "value":7.5107}
,{"word": "dept", "value":4.90801}
,{"word": "mmi", "value":4.73812}
,{"word": "questionner", "value":17.4179}
,{"word": "les", "value":0.773718}
,{"word": "humanités", "value":13.5343}
,{"word": "numériques", "value":13.3803}
,{"word": "perspectives", "value":12.1335}
,{"word": "croisées", "value":13.6351}
,{"word": "de", "value":0.686046}
,{"word": "la", "value":0.760075}
,{"word": "collecte", "value":10.4561}
,{"word": "des", "value":1.18365}
,{"word": "données", "value":1.43336}
,{"word": "sociales", "value":7.41153}
,{"word": "ou", "value":1.53658}
,{"word": "des", "value":1.18365}
,{"word": "corpus", "value":9.83059}
,{"word": "numériques", "value":13.3803}
,{"word": "à", "value":0.651841}
,{"word": "l", "value":0.862406}
,{"word": "émergence", "value":7.45303}
,{"word": "du", "value":1.27587}
,{"word": "sens", "value":8.68675}
,{"word": "université", "value":5.34417}
,{"word": "de", "value":0.686046}
,{"word": "cergy", "value":46.7787}
,{"word": "pontoise", "value":36.1198}
,{"word": "sites", "value":5.01352}
,{"word": "des", "value":1.18365}
,{"word": "chênes", "value":7.5107}
,{"word": "salle", "value":2.99437}
,{"word": "rdc", "value":5.6389}
,{"word": "avril", "value":3.66106}
,{"word": "accès", "value":4.15396}
,{"word": "http", "value":0.555942}
,{"word": "www", "value":1.19991}
,{"word": "u", "value":8.45807}
,{"word": "cergy", "value":46.7787}
,{"word": "fr", "value":0.680772}
,{"word": "resources", "value":3.88636}
,{"word": "communication", "value":1.7346}
,{"word": "sites", "value":5.01352}
,{"word": "chenes", "value":7.5107}
,{"word": "pdf", "value":1.60807}
,{"word": "download", "value":4.3537}
,{"word": "true", "value":6.25794}
,{"word": "journée", "value":11.6771}
,{"word": "d", "value":0.248896}
,{"word": "études", "value":2.477}
,{"word": "coordonnée", "value":7.10524}
,{"word": "par", "value":1.78036}
,{"word": "julien", "value":20.1109}
,{"word": "longhi", "value":29.0298}
,{"word": "université", "value":5.34417}
,{"word": "de", "value":0.686046}
,{"word": "cergy", "value":46.7787}
,{"word": "pontoise", "value":36.1198}
,{"word": "iut", "value":7.64358}
,{"word": "crtf", "value":12.2488}
,{"word": "pôle", "value":3.48535}
,{"word": "lascod", "value":7.5107}
,{"word": "ea", "value":15.0448}
,{"word": "dans", "value":0.559558}
,{"word": "le", "value":0.664168}
,{"word": "cadre", "value":1.22006}
,{"word": "du", "value":1.27587}
,{"word": "projet", "value":6.39421}
,{"word": "de", "value":0.686046}
,{"word": "recherche", "value":0.518608}
,{"word": "humanum", "value":14.2105}
,{"word": "dj", "value":15.0214}
,{"word": "humanités", "value":13.5343}
,{"word": "numériques", "value":13.3803}
,{"word": "et", "value":0.622499}
,{"word": "data", "value":1.32862}
,{"word": "journalisme", "value":5.43126}
,{"word": "le", "value":0.664168}
,{"word": "cas", "value":3.21068}
,{"word": "du", "value":1.27587}
,{"word": "lexique", "value":9.47623}
,{"word": "politique", "value":6.65731}
,{"word": "soutenu", "value":3.52172}
,{"word": "par", "value":1.78036}
,{"word": "la", "value":0.760075}
,{"word": "fondation", "value":4.76986}
,{"word": "de", "value":0.686046}
,{"word": "l", "value":0.862406}
,{"word": "université", "value":5.34417}
,{"word": "de", "value":0.686046}
,{"word": "cergy", "value":46.7787}
,{"word": "pontoise", "value":36.1198}
,{"word": "h", "value":45.6702}
,{"word": "h", "value":45.6702}
,{"word": "accueil", "value":2.46085}
,{"word": "h", "value":45.6702}
,{"word": "h", "value":45.6702}
,{"word": "julien", "value":20.1109}
,{"word": "longhi", "value":29.0298}
,{"word": "présentation", "value":1.60398}
,{"word": "du", "value":1.27587}
,{"word": "projet", "value":6.39421}
,{"word": "humanum", "value":14.2105}
,{"word": "dj", "value":15.0214}
,{"word": "et", "value":0.622499}
,{"word": "de", "value":0.686046}
,{"word": "la", "value":0.760075}
,{"word": "journée", "value":11.6771}
,{"word": "h", "value":45.6702}
,{"word": "h", "value":45.6702}
,{"word": "agata", "value":6.12441}
,{"word": "jackiewicz", "value":6.12441}
,{"word": "université", "value":5.34417}
,{"word": "paris", "value":0.94826}
,{"word": "sorbonne", "value":2.75281}
,{"word": "stih", "value":5.80596}
,{"word": "ea", "value":15.0448}
,{"word": "hashtags", "value":6.25794}
,{"word": "formes", "value":2.70668}
,{"word": "fonctions", "value":3.95536}
,{"word": "et", "value":0.622499}
,{"word": "usages", "value":2.72739}
,{"word": "h", "value":45.6702}
,{"word": "h", "value":45.6702}
,{"word": "pause", "value":9.36734}
,{"word": "h", "value":45.6702}
,{"word": "h", "value":45.6702}
,{"word": "boris", "value":7.5107}
,{"word": "borzic", "value":7.5107}
,{"word": "université", "value":5.34417}
,{"word": "de", "value":0.686046}
,{"word": "cergy", "value":46.7787}
,{"word": "pontoise", "value":36.1198}
,{"word": "etis", "value":15.9404}
,{"word": "umr", "value":5.60639}
,{"word": "cnrs", "value":6.33754}
,{"word": "extraction", "value":1.53182}
,{"word": "de", "value":0.686046}
,{"word": "tweets", "value":4.94575}
,{"word": "à", "value":0.651841}
,{"word": "partir", "value":1.68914}
,{"word": "d", "value":0.248896}
,{"word": "un", "value":0.671483}
,{"word": "découpage", "value":6.81756}
,{"word": "de", "value":0.686046}
,{"word": "communautés", "value":2.21489}
,{"word": "cohérentes", "value":6.41209}
,{"word": "cas", "value":3.21068}
,{"word": "des", "value":1.18365}
,{"word": "personnalités", "value":4.98498}
,{"word": "politiques", "value":3.41636}
,{"word": "françaises", "value":4.94575}
,{"word": "h", "value":45.6702}
,{"word": "h", "value":45.6702}
,{"word": "olivier", "value":2.95158}
,{"word": "bertrand", "value":4.27203}
,{"word": "université", "value":5.34417}
,{"word": "de", "value":0.686046}
,{"word": "cergy", "value":46.7787}
,{"word": "pontoise", "value":36.1198}
,{"word": "ldi", "value":5.71894}
,{"word": "umr", "value":5.60639}
,{"word": "cnrs", "value":6.33754}
,{"word": "lexique", "value":9.47623}
,{"word": "politique", "value":6.65731}
,{"word": "et", "value":0.622499}
,{"word": "perspective", "value":3.86005}
,{"word": "diachronique", "value":5.80596}
,{"word": "h", "value":45.6702}
,{"word": "h", "value":45.6702}
,{"word": "pause", "value":9.36734}
,{"word": "h", "value":45.6702}
,{"word": "h", "value":45.6702}
,{"word": "julien", "value":20.1109}
,{"word": "velcin", "value":3.79713}
,{"word": "université", "value":5.34417}
,{"word": "lyon", "value":1.8777}
,{"word": "eric", "value":2.33455}
,{"word": "ea", "value":15.0448}
,{"word": "analyser", "value":3.18657}
,{"word": "l", "value":0.862406}
,{"word": "image", "value":2.71079}
,{"word": "de", "value":0.686046}
,{"word": "marque", "value":5.80596}
,{"word": "véhiculée", "value":7.10524}
,{"word": "par", "value":1.78036}
,{"word": "les", "value":0.773718}
,{"word": "médias", "value":3.7612}
,{"word": "sociaux", "value":1.82543}
,{"word": "un", "value":0.671483}
,{"word": "aperçu", "value":4.31203}
,{"word": "du", "value":1.27587}
,{"word": "projet", "value":6.39421}
,{"word": "imagiweb", "value":5.25941}
,{"word": "h", "value":45.6702}
,{"word": "h", "value":45.6702}
,{"word": "mathieu", "value":3.154}
,{"word": "valette", "value":4.70734}
,{"word": "inalco", "value":4.14341}
,{"word": "ertim", "value":4.67749}
,{"word": "ea", "value":15.0448}
,{"word": "quelle", "value":3.60873}
,{"word": "sémantique", "value":1.62738}
,{"word": "de", "value":0.686046}
,{"word": "corpus", "value":9.83059}
,{"word": "pour", "value":0.187864}
,{"word": "les", "value":0.773718}
,{"word": "humanités", "value":13.5343}
,{"word": "numériques", "value":13.3803}
,{"word": "h", "value":45.6702}
,{"word": "h", "value":45.6702}
,{"word": "pause", "value":9.36734}
,{"word": "h", "value":45.6702}
,{"word": "h", "value":45.6702}
,{"word": "clair", "value":6.41209}
,{"word": "antoine", "value":3.36757}
,{"word": "veyrier", "value":7.5107}
,{"word": "télécom", "value":3.17997}
,{"word": "paristech", "value":3.53102}
,{"word": "ltci", "value":5.56479}
,{"word": "umr", "value":5.60639}
,{"word": "cnrs", "value":6.33754}
,{"word": "pratiques", "value":2.1975}
,{"word": "discursives", "value":5.56479}
,{"word": "et", "value":0.622499}
,{"word": "intelligibilité", "value":6.81756}
,{"word": "de", "value":0.686046}
,{"word": "l", "value":0.862406}
,{"word": "action", "value":3.43317}
,{"word": "sur", "value":0.260779}
,{"word": "twitter", "value":2.90553}
,{"word": "h", "value":45.6702}
,{"word": "h", "value":45.6702}
,{"word": "claudia", "value":9.81603}
,{"word": "marinica", "value":10.8625}
,{"word": "université", "value":5.34417}
,{"word": "de", "value":0.686046}
,{"word": "cergy", "value":46.7787}
,{"word": "pontoise", "value":36.1198}
,{"word": "ucp", "value":16.6944}
,{"word": "iut", "value":7.64358}
,{"word": "etis", "value":15.9404}
,{"word": "ucp", "value":16.6944}
,{"word": "ensea", "value":10.5188}
,{"word": "cnrs", "value":6.33754}
,{"word": "synthèse", "value":3.3135}
,{"word": "des", "value":1.18365}
,{"word": "échanges", "value":4.8586}
,{"word": "et", "value":0.622499}
,{"word": "perspectives", "value":12.1335}
,{"word": "le", "value":0.664168}
,{"word": "projet", "value":6.39421}
,{"word": "comédi", "value":7.5107}
,{"word": "h", "value":45.6702}
,{"word": "h", "value":45.6702}
,{"word": "julien", "value":20.1109}
,{"word": "longhi", "value":29.0298}
,{"word": "derniers", "value":3.62914}
,{"word": "échanges", "value":4.8586}
,{"word": "et", "value":0.622499}
,{"word": "conclusion", "value":4.62033}
]}
