{"text":1190,"subject":[
{"word": "fwd", "value":8.79438}
,{"word": "fwd", "value":8.79438}
,{"word": "appel", "value":1.2941}
,{"word": "à", "value":1.10465}
,{"word": "contributions", "value":4.25261}
,{"word": "workshop", "value":4.59293}
,{"word": "affect", "value":6.00663}
,{"word": "compagnon", "value":6.12441}
,{"word": "artificiel", "value":5.80596}
,{"word": "interaction", "value":5.06836}
,{"word": "wacai", "value":5.90127}
,{"word": "juin", "value":3.5125}
,{"word": "er", "value":4.0142}
,{"word": "juillet", "value":4.83656}
,{"word": "rouen", "value":5.20812}
,{"word": "fin", "value":4.6485}
,{"word": "avril", "value":4.39719}
,{"word": "fwd", "value":8.79438}
,{"word": "fwd", "value":8.79438}
,{"word": "appel", "value":1.2941}
,{"word": "à", "value":1.10465}
,{"word": "contributions", "value":4.25261}
,{"word": "workshop", "value":4.59293}
,{"word": "affect", "value":6.00663}
,{"word": "compagnon", "value":6.12441}
,{"word": "artificiel", "value":5.80596}
,{"word": "interaction", "value":5.06836}
,{"word": "wacai", "value":5.90127}
,{"word": "juin", "value":3.5125}
,{"word": "er", "value":4.0142}
,{"word": "juillet", "value":4.83656}
,{"word": "rouen", "value":5.20812}
,{"word": "fin", "value":4.6485}
,{"word": "avril", "value":4.39719}
],"content":[
{"word": "appel", "value":1.07616}
,{"word": "à", "value":0.651841}
,{"word": "contributions", "value":3.6679}
,{"word": "workshop", "value":9.42377}
,{"word": "francophone", "value":2.29305}
,{"word": "affect", "value":4.94575}
,{"word": "compagnon", "value":5.43126}
,{"word": "appel", "value":1.07616}
,{"word": "à", "value":0.651841}
,{"word": "contributions", "value":3.6679}
,{"word": "workshop", "value":9.42377}
,{"word": "francophone", "value":2.29305}
,{"word": "affect", "value":4.94575}
,{"word": "compagnon", "value":5.43126}
,{"word": "artificiel", "value":4.09298}
,{"word": "interaction", "value":6.21787}
,{"word": "wacai", "value":23.8493}
,{"word": "juin", "value":3.39613}
,{"word": "er", "value":4.69184}
,{"word": "juillet", "value":4.50642}
,{"word": "à", "value":0.651841}
,{"word": "rouen", "value":6.32085}
,{"word": "http", "value":0.555942}
,{"word": "wacai", "value":23.8493}
,{"word": "litislab", "value":5.06836}
,{"word": "fr", "value":0.170193}
,{"word": "l", "value":0.862406}
,{"word": "objectif", "value":1.36545}
,{"word": "du", "value":0.364534}
,{"word": "workshop", "value":9.42377}
,{"word": "wacai", "value":23.8493}
,{"word": "est", "value":1.26207}
,{"word": "de", "value":0.285853}
,{"word": "réunir", "value":2.88084}
,{"word": "les", "value":1.39269}
,{"word": "recherches", "value":1.92346}
,{"word": "et", "value":0.978212}
,{"word": "développements", "value":2.81936}
,{"word": "en", "value":0.458703}
,{"word": "cours", "value":3.33722}
,{"word": "autour", "value":1.72381}
,{"word": "des", "value":1.06528}
,{"word": "agents", "value":5.06106}
,{"word": "conversationnels", "value":8.8853}
,{"word": "animés", "value":10.627}
,{"word": "aca", "value":11.2778}
,{"word": "et", "value":0.978212}
,{"word": "des", "value":1.06528}
,{"word": "robots", "value":8.28682}
,{"word": "sociaux", "value":5.47628}
,{"word": "cette", "value":1.6447}
,{"word": "rencontre", "value":2.83321}
,{"word": "est", "value":1.26207}
,{"word": "plus", "value":0.742786}
,{"word": "particulièrement", "value":2.41084}
,{"word": "centrée", "value":4.1608}
,{"word": "sur", "value":0.782336}
,{"word": "l", "value":0.862406}
,{"word": "étude", "value":2.39271}
,{"word": "la", "value":0.168906}
,{"word": "modélisation", "value":1.64141}
,{"word": "le", "value":0.332084}
,{"word": "développement", "value":1.50929}
,{"word": "et", "value":0.978212}
,{"word": "l", "value":0.862406}
,{"word": "évaluation", "value":1.98525}
,{"word": "de", "value":0.285853}
,{"word": "l", "value":0.862406}
,{"word": "interaction", "value":6.21787}
,{"word": "de", "value":0.285853}
,{"word": "systèmes", "value":1.21084}
,{"word": "interactifs", "value":4.39719}
,{"word": "avec", "value":0.635472}
,{"word": "leurs", "value":1.47882}
,{"word": "partenaires", "value":3.12868}
,{"word": "humains", "value":3.52172}
,{"word": "ou", "value":2.56097}
,{"word": "artefactuels", "value":6.81756}
,{"word": "a", "value":0.709977}
,{"word": "l", "value":0.862406}
,{"word": "interface", "value":3.23404}
,{"word": "entre", "value":2.21923}
,{"word": "sciences", "value":2.69267}
,{"word": "de", "value":0.285853}
,{"word": "l", "value":0.862406}
,{"word": "ingénieur", "value":2.30122}
,{"word": "et", "value":0.978212}
,{"word": "sciences", "value":2.69267}
,{"word": "humaines", "value":2.70668}
,{"word": "et", "value":0.978212}
,{"word": "sociales", "value":2.47051}
,{"word": "l", "value":0.862406}
,{"word": "ambition", "value":4.25261}
,{"word": "de", "value":0.285853}
,{"word": "wacai", "value":23.8493}
,{"word": "est", "value":1.26207}
,{"word": "d", "value":0.165931}
,{"word": "appréhender", "value":4.09298}
,{"word": "l", "value":0.862406}
,{"word": "interaction", "value":6.21787}
,{"word": "personne", "value":2.43241}
,{"word": "système", "value":2.02383}
,{"word": "dans", "value":0.279779}
,{"word": "toute", "value":2.09238}
,{"word": "sa", "value":2.16122}
,{"word": "complexité", "value":3.24101}
,{"word": "biologique", "value":5.20812}
,{"word": "linguistique", "value":2.88084}
,{"word": "sociale", "value":3.30601}
,{"word": "culturelle", "value":5.11281}
,{"word": "et", "value":0.978212}
,{"word": "émotionnelle", "value":4.98498}
,{"word": "après", "value":2.39872}
,{"word": "les", "value":1.39269}
,{"word": "précédentes", "value":3.94117}
,{"word": "éditions", "value":3.39983}
,{"word": "bi", "value":4.3537}
,{"word": "annuelles", "value":5.80596}
,{"word": "du", "value":0.364534}
,{"word": "workshop", "value":9.42377}
,{"word": "waca", "value":6.59441}
,{"word": "organisées", "value":2.73579}
,{"word": "successivement", "value":5.90127}
,{"word": "à", "value":0.651841}
,{"word": "grenoble", "value":4.42477}
,{"word": "à", "value":0.651841}
,{"word": "toulouse", "value":2.05112}
,{"word": "à", "value":0.651841}
,{"word": "paris", "value":0.94826}
,{"word": "à", "value":0.651841}
,{"word": "lille", "value":2.72739}
,{"word": "et", "value":0.978212}
,{"word": "wacai", "value":23.8493}
,{"word": "à", "value":0.651841}
,{"word": "grenoble", "value":4.42477}
,{"word": "cette", "value":1.6447}
,{"word": "nouvelle", "value":2.57264}
,{"word": "édition", "value":1.93855}
,{"word": "se", "value":0.848849}
,{"word": "déroulera", "value":2.50676}
,{"word": "à", "value":0.651841}
,{"word": "rouen", "value":6.32085}
,{"word": "le", "value":0.332084}
,{"word": "juin", "value":3.39613}
,{"word": "et", "value":0.978212}
,{"word": "er", "value":4.69184}
,{"word": "juillet", "value":4.50642}
,{"word": "les", "value":1.39269}
,{"word": "contributions", "value":3.6679}
,{"word": "attendues", "value":3.09186}
,{"word": "en", "value":0.458703}
,{"word": "français", "value":1.58378}
,{"word": "ou", "value":2.56097}
,{"word": "en", "value":0.458703}
,{"word": "anglais", "value":1.79203}
,{"word": "sont", "value":0.593494}
,{"word": "de", "value":0.285853}
,{"word": "trois", "value":2.14707}
,{"word": "ordres", "value":5.56479}
,{"word": "des", "value":1.06528}
,{"word": "articles", "value":2.64899}
,{"word": "scientifiques", "value":1.63577}
,{"word": "max", "value":6.84946}
,{"word": "pages", "value":4.08991}
,{"word": "des", "value":1.06528}
,{"word": "revues", "value":3.8344}
,{"word": "de", "value":0.285853}
,{"word": "questions", "value":2.07045}
,{"word": "ou", "value":2.56097}
,{"word": "des", "value":1.06528}
,{"word": "états", "value":4.12631}
,{"word": "de", "value":0.285853}
,{"word": "l", "value":0.862406}
,{"word": "art", "value":2.6864}
,{"word": "max", "value":6.84946}
,{"word": "pages", "value":4.08991}
,{"word": "notamment", "value":1.99325}
,{"word": "sur", "value":0.782336}
,{"word": "les", "value":1.39269}
,{"word": "liens", "value":2.6864}
,{"word": "entre", "value":2.21923}
,{"word": "les", "value":1.39269}
,{"word": "problématiques", "value":1.97337}
,{"word": "communes", "value":3.45892}
,{"word": "et", "value":0.978212}
,{"word": "les", "value":1.39269}
,{"word": "spécificités", "value":3.77303}
,{"word": "des", "value":1.06528}
,{"word": "communautés", "value":2.21489}
,{"word": "aca", "value":11.2778}
,{"word": "et", "value":0.978212}
,{"word": "robotique", "value":3.26221}
,{"word": "des", "value":1.06528}
,{"word": "descriptions", "value":4.51497}
,{"word": "de", "value":0.285853}
,{"word": "réalisations", "value":3.99916}
,{"word": "ou", "value":2.56097}
,{"word": "d", "value":0.165931}
,{"word": "expérimentations", "value":3.39167}
,{"word": "en", "value":0.458703}
,{"word": "cours", "value":3.33722}
,{"word": "pages", "value":4.08991}
,{"word": "sur", "value":0.782336}
,{"word": "les", "value":1.39269}
,{"word": "domaines", "value":1.60534}
,{"word": "de", "value":0.285853}
,{"word": "l", "value":0.862406}
,{"word": "informatique", "value":0.787473}
,{"word": "affective", "value":4.73812}
,{"word": "le", "value":0.332084}
,{"word": "traitement", "value":1.32039}
,{"word": "des", "value":1.06528}
,{"word": "signaux", "value":4.59293}
,{"word": "sociaux", "value":5.47628}
,{"word": "les", "value":1.39269}
,{"word": "agents", "value":5.06106}
,{"word": "conversationnels", "value":8.8853}
,{"word": "animés", "value":10.627}
,{"word": "et", "value":0.978212}
,{"word": "les", "value":1.39269}
,{"word": "robots", "value":8.28682}
,{"word": "sociaux", "value":5.47628}
,{"word": "dates", "value":1.44808}
,{"word": "importantes", "value":1.61768}
,{"word": "soumission", "value":1.22657}
,{"word": "des", "value":1.06528}
,{"word": "articles", "value":2.64899}
,{"word": "avril", "value":1.83053}
,{"word": "notification", "value":1.50929}
,{"word": "aux", "value":0.616034}
,{"word": "auteurs", "value":1.45744}
,{"word": "mai", "value":3.29699}
,{"word": "version", "value":1.69359}
,{"word": "finale", "value":2.36904}
,{"word": "mai", "value":3.29699}
,{"word": "ce", "value":0.80262}
,{"word": "courrier", "value":3.61888}
,{"word": "électronique", "value":2.53053}
,{"word": "ne", "value":1.60671}
,{"word": "contient", "value":4.19652}
,{"word": "aucun", "value":4.0142}
,{"word": "virus", "value":4.0142}
,{"word": "ou", "value":2.56097}
,{"word": "logiciel", "value":2.76143}
,{"word": "malveillant", "value":5.43126}
,{"word": "parce", "value":4.59293}
,{"word": "que", "value":0.773144}
,{"word": "la", "value":0.168906}
,{"word": "protection", "value":3.62914}
,{"word": "avast", "value":9.35498}
,{"word": "antivirus", "value":4.70734}
,{"word": "est", "value":1.26207}
,{"word": "active", "value":4.37521}
,{"word": "http", "value":0.555942}
,{"word": "www", "value":0.599953}
,{"word": "avast", "value":9.35498}
,{"word": "com", "value":1.43077}
]}
