{"text":2930,"subject":[
{"word": "journée", "value":3.09791}
,{"word": "clustering", "value":5.90127}
,{"word": "octobre", "value":4.02946}
,{"word": "journée", "value":3.09791}
,{"word": "clustering", "value":5.90127}
,{"word": "octobre", "value":4.02946}
],"content":[
{"word": "bonjour", "value":1.12467}
,{"word": "bonjour", "value":1.12467}
,{"word": "orange", "value":6.79966}
,{"word": "labs", "value":10.483}
,{"word": "lannion", "value":4.1785}
,{"word": "le", "value":0.996252}
,{"word": "cnrs", "value":1.26751}
,{"word": "nancy", "value":6.32085}
,{"word": "le", "value":0.996252}
,{"word": "loria", "value":3.2766}
,{"word": "nancy", "value":6.32085}
,{"word": "le", "value":0.996252}
,{"word": "lifo", "value":4.33265}
,{"word": "orléans", "value":4.1785}
,{"word": "eric", "value":2.33455}
,{"word": "lyon", "value":1.8777}
,{"word": "le", "value":0.996252}
,{"word": "li", "value":4.12631}
,{"word": "tours", "value":3.50337}
,{"word": "le", "value":0.996252}
,{"word": "limos", "value":4.49028}
,{"word": "clermont", "value":3.11626}
,{"word": "ferrand", "value":3.18657}
,{"word": "à", "value":0.16296}
,{"word": "travers", "value":2.60173}
,{"word": "certains", "value":3.34404}
,{"word": "de", "value":0.0857558}
,{"word": "leurs", "value":1.47882}
,{"word": "représentants", "value":5.15933}
,{"word": "se", "value":0.848849}
,{"word": "sont", "value":0.593494}
,{"word": "associés", "value":3.25509}
,{"word": "pour", "value":0.187864}
,{"word": "organiser", "value":3.57888}
,{"word": "une", "value":0.622799}
,{"word": "journée", "value":3.89237}
,{"word": "scientifique", "value":1.53562}
,{"word": "sur", "value":0.782336}
,{"word": "la", "value":0.253358}
,{"word": "thématique", "value":2.25061}
,{"word": "du", "value":0.364534}
,{"word": "clustering", "value":6.18373}
,{"word": "et", "value":0.0889284}
,{"word": "du", "value":0.364534}
,{"word": "coclustering", "value":5.6389}
,{"word": "elle", "value":1.86349}
,{"word": "aura", "value":1.98725}
,{"word": "lieu", "value":1.09643}
,{"word": "le", "value":0.996252}
,{"word": "mardi", "value":2.69042}
,{"word": "octobre", "value":2.12163}
,{"word": "à", "value":0.16296}
,{"word": "issy", "value":6.12441}
,{"word": "les", "value":0.773718}
,{"word": "moulineaux", "value":6.12441}
,{"word": "dans", "value":0.559558}
,{"word": "les", "value":0.773718}
,{"word": "locaux", "value":3.94117}
,{"word": "d", "value":0.248896}
,{"word": "orange", "value":6.79966}
,{"word": "labs", "value":10.483}
,{"word": "la", "value":0.253358}
,{"word": "journée", "value":3.89237}
,{"word": "sera", "value":1.10218}
,{"word": "constituée", "value":4.83656}
,{"word": "essentiellement", "value":4.56627}
,{"word": "d", "value":0.248896}
,{"word": "exposés", "value":3.47646}
,{"word": "invités", "value":1.79203}
,{"word": "mais", "value":2.84105}
,{"word": "aussi", "value":1.58378}
,{"word": "d", "value":0.248896}
,{"word": "une", "value":0.622799}
,{"word": "assez", "value":4.31203}
,{"word": "longue", "value":4.31203}
,{"word": "session", "value":2.34878}
,{"word": "posters", "value":6.12438}
,{"word": "pendant", "value":3.17341}
,{"word": "le", "value":0.996252}
,{"word": "déjeuner", "value":3.58873}
,{"word": "les", "value":0.773718}
,{"word": "posters", "value":6.12438}
,{"word": "seront", "value":1.21084}
,{"word": "acceptés", "value":2.82395}
,{"word": "sur", "value":0.782336}
,{"word": "sélection", "value":2.57264}
,{"word": "après", "value":2.39872}
,{"word": "la", "value":0.253358}
,{"word": "réception", "value":2.19014}
,{"word": "de", "value":0.0857558}
,{"word": "résumés", "value":2.67442}
,{"word": "de", "value":0.0857558}
,{"word": "deux", "value":1.31223}
,{"word": "pages", "value":1.3633}
,{"word": "décrivant", "value":3.92719}
,{"word": "les", "value":0.773718}
,{"word": "travaux", "value":1.26073}
,{"word": "qui", "value":0.734767}
,{"word": "seraient", "value":4.07672}
,{"word": "présentés", "value":3.41636}
,{"word": "sur", "value":0.782336}
,{"word": "le", "value":0.996252}
,{"word": "poster", "value":3.09186}
,{"word": "le", "value":0.996252}
,{"word": "programme", "value":1.16244}
,{"word": "n", "value":1.3633}
,{"word": "est", "value":0.315517}
,{"word": "pas", "value":1.2941}
,{"word": "encore", "value":2.40173}
,{"word": "constitué", "value":4.1785}
,{"word": "mais", "value":2.84105}
,{"word": "vous", "value":0.945439}
,{"word": "pouvez", "value":3.16043}
,{"word": "déjà", "value":2.42311}
,{"word": "réserver", "value":5.71894}
,{"word": "cette", "value":0.822349}
,{"word": "date", "value":1.08422}
,{"word": "dans", "value":0.559558}
,{"word": "votre", "value":2.03843}
,{"word": "calendrier", "value":2.87113}
,{"word": "cordialement", "value":1.22378}
,{"word": "toutes", "value":1.87235}
,{"word": "les", "value":0.773718}
,{"word": "infos", "value":4.80265}
,{"word": "ici", "value":2.80117}
,{"word": "http", "value":0.277971}
,{"word": "www", "value":0.599953}
,{"word": "vincentlemaire", "value":4.83656}
,{"word": "labs", "value":10.483}
,{"word": "fr", "value":0.170193}
,{"word": "clustering", "value":6.18373}
]}
